imcflibs3/__init__.py
imcflibs3/iotools.py
imcflibs3/log.py
imcflibs3/pathtools.py
imcflibs3/strtools.py
imcflibs3-1.5.0a0.dist-info/LICENSE.txt
imcflibs3-1.5.0a0.dist-info/METADATA
imcflibs3-1.5.0a0.dist-info/WHEEL
imcflibs3-1.5.0a0.dist-info/RECORD
