Metadata-Version: 2.1
Name: imcflibs3
Version: 1.5.0a0
Summary: Small collection of paths/io/string helper functions.
License: GPL-3.0-or-later
Author: Niko Ehrenfeuchter
Author-email: nikolaus.ehrenfeuchter@unibas.ch
Requires-Python: >=3.8,<4.0
Classifier: License :: OSI Approved :: GNU General Public License v3 or later (GPLv3+)
Classifier: Programming Language :: Python :: 3
Classifier: Programming Language :: Python :: 3.8
Classifier: Programming Language :: Python :: 3.9
Classifier: Programming Language :: Python :: 3.10
Classifier: Programming Language :: Python :: 3.11
Project-URL: Changelog, https://github.com/imcf/python-imcflibs3/blob/main/CHANGELOG.md
Project-URL: Documentation, https://imcf.one/apidocs/imcflibs3/imcflibs3.html
Project-URL: Organisation Homepage, https://imcf.one/
